thinmaxflow/__init__.py
thinmaxflow/_maxflow.cp312-win_amd64.pyd
thinmaxflow-0.1.6.dist-info/licenses/LICENSE
thinmaxflow-0.1.6.dist-info/METADATA
thinmaxflow-0.1.6.dist-info/WHEEL
thinmaxflow-0.1.6.dist-info/top_level.txt
thinmaxflow-0.1.6.dist-info/RECORD
